Metadata-Version: 2.1
Name: tap-square
Version: 2.3.1
Summary: Singer.io tap for extracting data from the Square API
Home-page: http://singer.io
Author: Stitch
License: UNKNOWN
Platform: UNKNOWN
Classifier: Programming Language :: Python :: 3 :: Only
Provides-Extra: dev
